README.md
setup.py
pybacklog/__init__.py
pybacklog.egg-info/PKG-INFO
pybacklog.egg-info/SOURCES.txt
pybacklog.egg-info/dependency_links.txt
pybacklog.egg-info/requires.txt
pybacklog.egg-info/top_level.txt