Metadata-Version: 1.1
Name: pybacklog
Version: 0.1.4
Summary: Backlog API v2 Client
Home-page: https://github.com/netmarkjp/pybacklog
Author: Toshiaki Baba
Author-email: toshiaki@netmark.jp
License: UNKNOWN
Platform: UNKNOWN
Classifier: Programming Language :: Python :: 2.7
Classifier: Programming Language :: Python :: 3.5
Classifier: Topic :: Utilities
